demo_publish/__about__.py
demo_publish/__init__.py
demo_publish/hejverden.py
demo_publish-0.0.4.dist-info/METADATA
demo_publish-0.0.4.dist-info/WHEEL
demo_publish-0.0.4.dist-info/licenses/LICENSE.txt
demo_publish-0.0.4.dist-info/RECORD
