Metadata-Version: 2.1
Name: demo-publish
Version: 0.0.4
Summary: This is a tester project to publish something
Project-URL: Documentation, https://github.com/unknown/demo-publish#readme
Project-URL: Issues, https://github.com/unknown/demo-publish/issues
Project-URL: Source, https://github.com/unknown/demo-publish
Author-email: flexfalk <sofu0284@gmail.com>
License-Expression: MIT
License-File: LICENSE.txt
Classifier: Development Status :: 4 - Beta
Classifier: Programming Language :: Python
Classifier: Programming Language :: Python :: 3.7
Classifier: Programming Language :: Python :: 3.8
Classifier: Programming Language :: Python :: 3.9
Classifier: Programming Language :: Python :: 3.10
Classifier: Programming Language :: Python :: 3.11
Classifier: Programming Language :: Python :: Implementation :: CPython
Classifier: Programming Language :: Python :: Implementation :: PyPy
Requires-Python: >=3.7
Requires-Dist: numpy
Requires-Dist: pandas
